AutoClusterML/AutoCluster.py
AutoClusterML/__init__.py
AutoClusterML-0.1.2.dist-info/LICENSE
AutoClusterML-0.1.2.dist-info/METADATA
AutoClusterML-0.1.2.dist-info/WHEEL
AutoClusterML-0.1.2.dist-info/top_level.txt
AutoClusterML-0.1.2.dist-info/RECORD
