Metadata-Version: 2.1
Name: AutoClusterML
Version: 0.1.2
Summary: This is a python package useful for the automated dimensionality reduction and clustering (both unsupervised and supervised).
Author: Sairam Adithya
Author-email: sairamadithya2002@gmail.com
Classifier: Programming Language :: Python :: 3
Classifier: License :: OSI Approved :: MIT License
Classifier: Operating System :: OS Independent
Requires-Python: >=3.6
License-File: LICENSE
